<?xml version="1.0" encoding="utf-8" ?>

<Patch>
  
   <Operation Class="PatchOperationAddModExtension">
    <xpath>/Defs/PawnKindDef[defName="ChjAndroidVillager"]</xpath>
    <value>
      <li Class="CombatExtended.LoadoutPropertiesExtension">
        <primaryMagazineCount>
          <min>3</min>
          <max>5</max>
        </primaryMagazineCount>
      </li>
    </value>
  </Operation>
  
  <Operation Class="PatchOperationAddModExtension">
    <xpath>/Defs/PawnKindDef[defName="ChjAndroidTownGuard"]</xpath>
    <value>
      <li Class="CombatExtended.LoadoutPropertiesExtension">
        <primaryMagazineCount>
          <min>3</min>
          <max>5</max>
        </primaryMagazineCount>
        <forcedSidearm>
          <sidearmMoney>
            <min>1600</min>
            <max>2200</max>
          </sidearmMoney>
          <weaponTags>
            <li>NonNeolithicOnlyMelee</li>
          </weaponTags>
          <magazineCount>
            <min>3</min>
            <max>5</max>
          </magazineCount>
        </forcedSidearm>
      </li>
    </value>
  </Operation>
  
  <Operation Class="PatchOperationAddModExtension">
    <xpath>/Defs/PawnKindDef[defName="ChjAndroidMercenaryGunner"]</xpath>
    <value>
      <li Class="CombatExtended.LoadoutPropertiesExtension">
        <primaryMagazineCount>
          <min>4</min>
          <max>5</max>
        </primaryMagazineCount>
        <forcedSidearm>
          <sidearmMoney>
            <min>1600</min>
            <max>2200</max>
          </sidearmMoney>
          <weaponTags>
            <li>NonNeolithicOnlyMelee</li>
          </weaponTags>
          <magazineCount>
            <min>3</min>
            <max>5</max>
          </magazineCount>
        </forcedSidearm>
      </li>
    </value>
  </Operation>
  
  <Operation Class="PatchOperationAddModExtension">
    <xpath>/Defs/PawnKindDef[defName="ChjAndroidMercenarySniper"]</xpath>
    <value>
      <li Class="CombatExtended.LoadoutPropertiesExtension">
        <primaryMagazineCount>
          <min>3</min>
          <max>5</max>
        </primaryMagazineCount>
      </li>
    </value>
  </Operation>
  
  <Operation Class="PatchOperationAddModExtension">
    <xpath>/Defs/PawnKindDef[defName="ChjAndroidMercenarySlasher"]</xpath>
    <value>
      <li Class="CombatExtended.LoadoutPropertiesExtension">
        <primaryMagazineCount>
          <min>3</min>
          <max>5</max>
        </primaryMagazineCount>
      </li>
    </value>
  </Operation>
  
  <Operation Class="PatchOperationAddModExtension">
    <xpath>/Defs/PawnKindDef[defName="ChjAndroidMercenaryHeavy"]</xpath>
    <value>
      <li Class="CombatExtended.LoadoutPropertiesExtension">
        <primaryMagazineCount>
          <min>3</min>
          <max>5</max>
        </primaryMagazineCount>
      </li>
    </value>
  </Operation>
  
</Patch>